runreporter/__init__.py
runreporter/email_config.py
runreporter/logger.py
runreporter/manager.py
runreporter/report.py
runreporter/transports.py
runreporter-1.0.0.dist-info/METADATA
runreporter-1.0.0.dist-info/WHEEL
runreporter-1.0.0.dist-info/top_level.txt
runreporter-1.0.0.dist-info/RECORD
