Metadata-Version: 2.4
Name: runreporter
Version: 1.0.0
Summary: Library for logging runtime errors and sending execution reports via Telegram and Email
Author: nosikmov
Requires-Python: >=3.9
Requires-Dist: requests>=2.31.0
